Metadata-Version: 2.1
Name: krok
Version: 1.0.0
Summary: Expose your local TCP server as Kubernetes service in remote cluster.
Home-page: https://github.com/smpio/krok
Author: Dmitry Bashkatov
Author-email: dbashkatov@gmail.com
License: MIT
Platform: UNKNOWN
Classifier: Intended Audience :: Developers
Classifier: Intended Audience :: System Administrators
Classifier: License :: OSI Approved :: MIT License
Classifier: Operating System :: MacOS
Classifier: Operating System :: POSIX :: Linux
Classifier: Programming Language :: Python :: 3
Classifier: Programming Language :: Python :: 3.6
Classifier: Programming Language :: Python :: 3 :: Only
Classifier: Topic :: Software Development
Classifier: Topic :: System :: Networking
